BSMILES/BSMILES.py
BSMILES/B_to_smiles.py
BSMILES/__init__.py
BSMILES-0.0.1.dist-info/LICENSE.txt
BSMILES-0.0.1.dist-info/METADATA
BSMILES-0.0.1.dist-info/WHEEL
BSMILES-0.0.1.dist-info/top_level.txt
BSMILES-0.0.1.dist-info/RECORD
