Metadata-Version: 2.1
Name: BSMILES
Version: 0.0.1
Summary: transformation between smiles and bsmiles
Home-page: https://github.com/LUJUANJUAN/BSMILES
Author: lu
Author-email: lu@gmail.com
License: UNKNOWN
Platform: UNKNOWN
Classifier: Programming Language :: Python :: 3
Classifier: License :: OSI Approved :: MIT License
Classifier: Operating System :: OS Independent
